README.md
setup.py
common/Dataset.py
common/TrainingTask.py
common/__init__.py
common/global_variable.py
common/log_commons.py
common/util/JsonConvert.py
common/util/__init__.py
common/util/common_utils.py
common/util/s3_utils.py
ddlworker_ec2.egg-info/PKG-INFO
ddlworker_ec2.egg-info/SOURCES.txt
ddlworker_ec2.egg-info/dependency_links.txt
ddlworker_ec2.egg-info/entry_points.txt
ddlworker_ec2.egg-info/requires.txt
ddlworker_ec2.egg-info/top_level.txt
main/__init__.py
main/utils.py
main/worker_entry.py
main/worker_main.py
worker/__init__.py
worker/worker_run.py
worker/worker_start.py
worker/hooks/__init__.py
worker/hooks/work_exec_hooks.py
worker/worker_log/__init__.py
worker/worker_log/worker_logger.py
worker/worker_util/__init__.py
worker/worker_util/worker_util.py