Metadata-Version: 2.1
Name: ddlworker-ec2
Version: 1.0.3
Summary: cli for distributed deep learning worker
Home-page: UNKNOWN
Author: YL & SW
Author-email: nedlitex0053@gmail.com
License: UNKNOWN
Platform: UNKNOWN
Classifier: Programming Language :: Python :: 3
Classifier: Operating System :: OS Independent
